test_mcp_oranges/__init__.py
test_mcp_oranges/server.py
test_mcp_oranges-0.1.3.dist-info/METADATA
test_mcp_oranges-0.1.3.dist-info/WHEEL
test_mcp_oranges-0.1.3.dist-info/entry_points.txt
test_mcp_oranges-0.1.3.dist-info/top_level.txt
test_mcp_oranges-0.1.3.dist-info/RECORD
