Metadata-Version: 2.4
Name: test-mcp-oranges
Version: 0.1.3
Summary: Add your description here
Requires-Python: >=3.10
Requires-Dist: mcp>=1.6.0
